examples/__init__.py
examples/urls.py
examples/management/__init__.py
examples/management/commands/__init__.py
examples/management/commands/load_fixtures.py
examples/restaurants/__init__.py
examples/restaurants/fixture.py
examples/restaurants/models.py
examples/restaurants/schema.py
examples/restaurants/urls.py
examples/restaurants/migrations/0001_initial.py
examples/restaurants/migrations/__init__.py
graphene_extensions/__init__.py
graphene_extensions/decorators.py
graphene_extensions/optimization.py
graphene_extensions/query.py
graphene_extensions/status.py
graphene_extensions/views.py
graphene_extensions/fields/__init__.py
graphene_extensions/fields/connections.py
graphene_extensions/fields/list.py
graphene_extensions/types/__init__.py
graphene_extensions/types/decorators.py
graphene_extensions/types/factories.py
graphene_extensions/types/model_type.py
graphene_extensions/types/registry.py
graphene_extensions/utils/__init__.py
graphene_extensions/utils/callables.py
graphene_extensions/utils/model_meta.py
graphene_extensions/utils/selectors.py
graphene_extensions/utils/singleton.py
graphene_extensions-0.1.0b4.dist-info/DESCRIPTION.rst
graphene_extensions-0.1.0b4.dist-info/METADATA
graphene_extensions-0.1.0b4.dist-info/RECORD
graphene_extensions-0.1.0b4.dist-info/WHEEL
graphene_extensions-0.1.0b4.dist-info/metadata.json
graphene_extensions-0.1.0b4.dist-info/top_level.txt
