Metadata-Version: 2.0
Name: graphene-extensions
Version: 0.1.0b4
Summary: GraphQL framework for django
Home-page: https://github.com/karol-gruszczyk/graphene-extenstions/
Author: Karol Gruszczyk
Author-email: karol.gruszczyk@gmail.com
License: MIT
Keywords: graphql framework django relay graphene
Platform: UNKNOWN
Classifier: Development Status :: 4 - Beta
Classifier: Programming Language :: Python :: 3 :: Only
Classifier: Programming Language :: Python :: 3
Classifier: Programming Language :: Python :: 3.6
Classifier: Programming Language :: Python :: 3.7
Classifier: License :: OSI Approved :: MIT License
Classifier: Operating System :: OS Independent
Requires-Python: ~=3.6
Requires-Dist: graphene (>=2.0<3)
Requires-Dist: django (>=1.10<2)
